[
  {
    "date": "1904-10-27",
    "fare": 0.05
  },
  {
    "date": "1948-07-01",
    "fare": 0.10
  },
  {
    "date": "1953-07-25",
    "fare": 0.15
  },
  {
    "date": "1966-07-05",
    "fare": 0.20
  },
  {
    "date": "1970-01-04",
    "fare": 0.30
  },
  {
    "date": "1972-01-01",
    "fare": 0.35
  },
  {
    "date": "1975-09-02",
    "fare": 0.50
  },
  {
    "date": "1980-06-28",
    "fare": 0.60
  },
  {
    "date": "1981-07-03",
    "fare": 0.75
  },
  {
    "date": "1984-01-02",
    "fare": 0.90
  },
  {
    "date": "1986-01-01",
    "fare": 1.00
  },
  {
    "date": "1990-01-01",
    "fare": 1.15
  },
  {
    "date": "1992-01-01",
    "fare": 1.25
  },
  {
    "date": "1995-11-12",
    "fare": 1.50
  },
  {
    "date": "2003-05-04",
    "fare": 2.00
  },
  {
    "date": "2009-06-28",
    "fare": 2.25
  },
  {
    "date": "2013-03-03",
    "fare": 2.50
  },
  {
    "date": "2015-03-22",
    "fare": 2.75
  },
  {
    "date": "2023-08-20",
    "fare": 2.90
  }
]
